setup.py
Products/__init__.py
Products.ScreenReaderNavigation.egg-info/PKG-INFO
Products.ScreenReaderNavigation.egg-info/SOURCES.txt
Products.ScreenReaderNavigation.egg-info/dependency_links.txt
Products.ScreenReaderNavigation.egg-info/entry_points.txt
Products.ScreenReaderNavigation.egg-info/namespace_packages.txt
Products.ScreenReaderNavigation.egg-info/not-zip-safe
Products.ScreenReaderNavigation.egg-info/requires.txt
Products.ScreenReaderNavigation.egg-info/top_level.txt
Products/ScreenReaderNavigation/__init__.py
Products/ScreenReaderNavigation/changes.txt
Products/ScreenReaderNavigation/configure.zcml
Products/ScreenReaderNavigation/navigation.py
Products/ScreenReaderNavigation/overrides.zcml
Products/ScreenReaderNavigation/readme.txt
Products/ScreenReaderNavigation/browser/__init__.py
Products/ScreenReaderNavigation/i18n/screenreadernavigation-no.po
Products/ScreenReaderNavigation/templates/navigation.pt
Products/ScreenReaderNavigation/templates/navigation_recurse.pt
docs/HISTORY.txt