Metadata-Version: 1.0
Name: Products.ScreenReaderNavigation
Version: 1.0.1b
Summary: Adds header-2 HTML to navigation portlet for accessibility
Home-page: http://www.nidelven-it.no/d
Author: Morten W. Petersen
Author-email: info@nidelven-it.no
License: GPL
Keywords: python plone accessibility navigation
Platform: UNKNOWN
Classifier: Programming Language :: Python
Classifier: Framework :: Plone
Classifier: License :: OSI Approved :: GNU General Public License v2 (GPLv2)
